__init__.py
data_ingestion.py
main.py
nonstandardcode.py
preprocessing.py
scoring.py
training.py
fsds_training-0.3.0.dist-info/METADATA
fsds_training-0.3.0.dist-info/WHEEL
fsds_training-0.3.0.dist-info/top_level.txt
fsds_training-0.3.0.dist-info/RECORD
