Metadata-Version: 2.4
Name: fsds-training
Version: 0.3.0
Summary: Add your description here
Requires-Python: >=3.12
Requires-Dist: numpy
Requires-Dist: pandas
Requires-Dist: scikit-learn>=1.6.1
Requires-Dist: six>=1.17.0
Provides-Extra: formatter
Requires-Dist: black; extra == "formatter"
Requires-Dist: isort; extra == "formatter"
Requires-Dist: flake8; extra == "formatter"
Provides-Extra: plot
Requires-Dist: matplotlib; extra == "plot"
Requires-Dist: seaborn; extra == "plot"
Provides-Extra: test
Requires-Dist: pytest; extra == "test"
